flipgenic/__init__.py
flipgenic/db_models.py
flipgenic-2.2.1.dist-info/LICENSE
flipgenic-2.2.1.dist-info/METADATA
flipgenic-2.2.1.dist-info/WHEEL
flipgenic-2.2.1.dist-info/top_level.txt
flipgenic-2.2.1.dist-info/RECORD
