Metadata-Version: 2.1
Name: flipgenic
Version: 2.2.1
Summary: High-speed conversational dialogue engine
Home-page: https://github.com/danth/flipgenic
Author: Daniel Thwaites
Author-email: danthwaites30@btinternet.com
License: UNKNOWN
Project-URL: Bug Reports, https://github.com/danth/flipgenic/issues
Project-URL: Source, https://github.com/danth/flipgenic
Keywords: conversation dialogue engine chat chatbot
Platform: UNKNOWN
Classifier: Development Status :: 3 - Alpha
Classifier: License :: OSI Approved :: GNU Affero General Public License v3
Classifier: Programming Language :: Python :: 3
Classifier: Programming Language :: Python :: 3.6
Classifier: Programming Language :: Python :: 3.7
Requires-Python: >=3.6,<4
License-File: LICENSE
Requires-Dist: sqlalchemy (<2,>=1.3)
Requires-Dist: ngt (<2,>=1)
Requires-Dist: spacy (<4,>=3)
Provides-Extra: docs
Requires-Dist: Sphinx (<4,>=3) ; extra == 'docs'
